exsource_tools/__init__.py
exsource_tools/cli.py
exsource_tools/enums.py
exsource_tools/exporters.py
exsource_tools/exsource.py
exsource_tools/tools.py
exsource_tools/utils.py
exsource_tools/schemas/exsource.schema.json
exsource_tools-0.0.9.dist-info/METADATA
exsource_tools-0.0.9.dist-info/WHEEL
exsource_tools-0.0.9.dist-info/entry_points.txt
exsource_tools-0.0.9.dist-info/licenses/LICENSE
exsource_tools-0.0.9.dist-info/RECORD
