Metadata-Version: 2.4
Name: exsource_tools
Version: 0.0.9
Summary: Python tools for using Exsource files.
Author-email: Julian Stirling <julian@julianstirling.co.uk>
License-File: LICENSE
Keywords: Documentation,Hardware
Classifier: License :: OSI Approved :: GNU Lesser General Public License v3 (LGPLv3)
Requires-Python: >=3.7
Requires-Dist: argparse
Requires-Dist: jsonschema
Requires-Dist: pyyaml>=5.1
Provides-Extra: dev
Requires-Dist: build; extra == 'dev'
Requires-Dist: colorama; extra == 'dev'
Requires-Dist: pylint; extra == 'dev'
Requires-Dist: twine; extra == 'dev'
